{
   "nodes": [
     {
        "name": "computeovsdpdk-0",
        "pm_addr": "10.37.146.181",
        "ports": [
            {
              "address": "e4:43:4b:5c:98:b1",
              "physical_network": "leaf1"
            }
        ],
        "arch": "x86_64",
        "pm_type": "pxe_ipmitool",
        "pm_user": "root",
        "pm_password": "calvin",
        "cpu": "1",
        "memory": "4096",
        "disk": "40",
        "resource_class": "computeovsdpdk"
     },
 {
        "name": "computesriov-0",
        "pm_addr": "10.37.146.177",
        "ports": [
            {
              "address": "e4:43:4b:4a:30:f1",
              "physical_network": "leaf1"
            }
        ],
        "arch": "x86_64",
        "pm_type": "pxe_ipmitool",
        "pm_user": "root",
        "pm_password": "calvin",
        "cpu": "1",
        "memory": "4096",
        "disk": "40",
        "resource_class": "computesriov"
     }

  ]
}
